bandgap_calc/__init__.py
bandgap_calc/gui.py
bandgap_calc-1.0.0.dist-info/METADATA
bandgap_calc-1.0.0.dist-info/WHEEL
bandgap_calc-1.0.0.dist-info/entry_points.txt
bandgap_calc-1.0.0.dist-info/top_level.txt
bandgap_calc-1.0.0.dist-info/RECORD
